ShiXunChameleon/Config.py
ShiXunChameleon/__init__.py
ShiXunChameleon/Cipher/BasicSIS.py
ShiXunChameleon/Cipher/CA.py
ShiXunChameleon/Cipher/Crypto.py
ShiXunChameleon/Cipher/Signature.py
ShiXunChameleon/Cipher/UserKeyPair.py
ShiXunChameleon/Cipher/__init__.py
ShiXunChameleon/IO/Converter.py
ShiXunChameleon/IO/Error.py
ShiXunChameleon/IO/Evaluate.py
ShiXunChameleon/IO/String.py
ShiXunChameleon/IO/__init__.py
ShiXunChameleon/IO/extract_CA.py
ShiXunChameleon/Math/Matrix.py
ShiXunChameleon/Math/Tools.py
ShiXunChameleon/Math/__init__.py
ShiXunChameleon-1.0.1.dist-info/LICENSE.txt
ShiXunChameleon-1.0.1.dist-info/METADATA
ShiXunChameleon-1.0.1.dist-info/WHEEL
ShiXunChameleon-1.0.1.dist-info/top_level.txt
ShiXunChameleon-1.0.1.dist-info/RECORD
